README.txt
quintagroup.dummylocking-overrides.zcml
setup.py
docs/HISTORY.txt
docs/INSTALL.txt
docs/LICENSE.GPL
docs/LICENSE.txt
quintagroup/__init__.py
quintagroup.dummylocking.egg-info/PKG-INFO
quintagroup.dummylocking.egg-info/SOURCES.txt
quintagroup.dummylocking.egg-info/dependency_links.txt
quintagroup.dummylocking.egg-info/entry_points.txt
quintagroup.dummylocking.egg-info/namespace_packages.txt
quintagroup.dummylocking.egg-info/not-zip-safe
quintagroup.dummylocking.egg-info/requires.txt
quintagroup.dummylocking.egg-info/top_level.txt
quintagroup/dummylocking/__init__.py
quintagroup/dummylocking/lockable.py
quintagroup/dummylocking/overrides.zcml