Metadata-Version: 1.0
Name: quintagroup.dummylocking
Version: 0.1
Summary: This package turns off Plone locking.
Home-page: http://svn.quintagroup.com/products/quintagroup.dummylocking
Author: Bohdan Koval (Quintagroup)
Author-email: koval@quintagroup.com
License: GPL
Keywords: plone locking
Platform: UNKNOWN
Classifier: Framework :: Plone
Classifier: Programming Language :: Python
Classifier: Topic :: Software Development :: Libraries :: Python Modules
